{
  "family": "laravel-task",
  "networkMode": "awsvpc",
  "requiresCompatibilities": ["FARGATE"],
  "cpu": "512",
  "memory": "1024",
  "executionRoleArn": "arn:aws:iam::YOUR_ACCOUNT_ID:role/ecsTaskExecutionRole",
  "taskRoleArn": "arn:aws:iam::YOUR_ACCOUNT_ID:role/ecsTaskRole",
  "containerDefinitions": [
    {
      "name": "laravel-app",
      "image": "YOUR_ACCOUNT_ID.dkr.ecr.us-east-1.amazonaws.com/laravel-app:latest",
      "essential": true,
      "portMappings": [
        {
          "containerPort": 80,
          "protocol": "tcp"
        }
      ],
      "environment": [
        {
          "name": "APP_ENV",
          "value": "production"
        },
        {
          "name": "APP_DEBUG",
          "value": "false"
        },
        {
          "name": "LOG_CHANNEL",
          "value": "stderr"
        },
        {
          "name": "DB_CONNECTION",
          "value": "mysql"
        },
        {
          "name": "CACHE_DRIVER",
          "value": "redis"
        },
        {
          "name": "SESSION_DRIVER",
          "value": "redis"
        },
        {
          "name": "QUEUE_CONNECTION",
          "value": "redis"
        }
      ],
      "secrets": [
        {
          "name": "APP_KEY",
          "valueFrom": "arn:aws:secretsmanager:us-east-1:YOUR_ACCOUNT_ID:secret:laravel/app-key"
        },
        {
          "name": "DB_HOST",
          "valueFrom": "arn:aws:secretsmanager:us-east-1:YOUR_ACCOUNT_ID:secret:laravel/db-host"
        },
        {
          "name": "DB_DATABASE",
          "valueFrom": "arn:aws:secretsmanager:us-east-1:YOUR_ACCOUNT_ID:secret:laravel/db-name"
        },
        {
          "name": "DB_USERNAME",
          "valueFrom": "arn:aws:secretsmanager:us-east-1:YOUR_ACCOUNT_ID:secret:laravel/db-username"
        },
        {
          "name": "DB_PASSWORD",
          "valueFrom": "arn:aws:secretsmanager:us-east-1:YOUR_ACCOUNT_ID:secret:laravel/db-password"
        },
        {
          "name": "REDIS_HOST",
          "valueFrom": "arn:aws:secretsmanager:us-east-1:YOUR_ACCOUNT_ID:secret:laravel/redis-host"
        }
      ],
      "logConfiguration": {
        "logDriver": "awslogs",
        "options": {
          "awslogs-group": "/ecs/laravel-app",
          "awslogs-region": "us-east-1",
          "awslogs-stream-prefix": "ecs"
        }
      },
      "healthCheck": {
        "command": [
          "CMD-SHELL",
          "curl -f http://localhost/health || exit 1"
        ],
        "interval": 30,
        "timeout": 5,
        "retries": 3,
        "startPeriod": 60
      }
    }
  ]
}
